{
  "日本": [
    "北海道",
    "青森県",
    "岩手県",
    "宮城県",
    "秋田県",
    "山形県",
    "福島県",
    "茨城県",
    "栃木県",
    "群馬県",
    "埼玉県",
    "千葉県",
    "東京都",
    "神奈川県",
    "新潟県",
    "富山県",
    "石川県",
    "福井県",
    "山梨県",
    "長野県",
    "岐阜県",
    "静岡県",
    "愛知県",
    "三重県",
    "滋賀県",
    "京都府",
    "大阪府",
    "兵庫県",
    "奈良県",
    "和歌山県",
    "鳥取県",
    "島根県",
    "岡山県",
    "広島県",
    "山口県",
    "徳島県",
    "香川県",
    "愛媛県",
    "高知県",
    "福岡県",
    "佐賀県",
    "長崎県",
    "熊本県",
    "大分県",
    "宮崎県",
    "鹿児島県",
    "沖縄県"
  ],
  "アメリカ": [
    "アラバマ州",
    "アラスカ州",
    "アリゾナ州",
    "アーカンソー州",
    "カリフォルニア州",
    "コロラド州",
    "コネチカット州",
    "デラウェア州",
    "フロリダ州",
    "ジョージア州",
    "ハワイ州",
    "アイダホ州",
    "イリノイ州",
    "インディアナ州",
    "アイオワ州",
    "カンザス州",
    "ケンタッキー州",
    "ルイジアナ州",
    "メイン州",
    "メリーランド州",
    "マサチューセッツ州",
    "ミシガン州",
    "ミネソタ州",
    "ミシシッピ州",
    "ミズーリ州",
    "モンタナ州",
    "ネブラスカ州",
    "ネバダ州",
    "ニューハンプシャー州",
    "ニュージャージー州",
    "ニューメキシコ州",
    "ニューヨーク州",
    "ノースカロライナ州",
    "ノースダコタ州",
    "オハイオ州",
    "オクラホマ州",
    "オレゴン州",
    "ペンシルベニア州",
    "ロードアイランド州",
    "サウスカロライナ州",
    "サウスダコタ州",
    "テネシー州",
    "テキサス州",
    "ユタ州",
    "バーモント州",
    "バージニア州",
    "ワシントン州",
    "ウェストバージニア州",
    "ウィスコンシン州",
    "ワイオミング州"
  ],
  "ドミニカ共和国": [
    "サントドミンゴ",
    "サンペドロ・デ・マコリス",
    "サンティアゴ",
    "ラ・ロマーナ",
    "プエルトプラタ",
    "ラ・ベガ",
    "アスア",
    "バニ",
    "イグエイ"
  ],
  "ベネズエラ": [
    "カラカス",
    "マラカイボ",
    "バレンシア",
    "マラカイ",
    "バルキシメト",
    "プエルトラクルス",
    "シウダーグアヤナ",
    "メリダ",
    "ラ・グアイラ"
  ],
  "キューバ": [
    "ハバナ",
    "サンティアゴ・デ・クーバ",
    "カマグエイ",
    "オルギン",
    "サンタクララ",
    "マタンサス",
    "ピナール・デル・リオ",
    "シエンフエゴス"
  ],
  "メキシコ": [
    "メキシコシティ",
    "ソノラ州",
    "シナロア州",
    "ヌエボレオン州",
    "ハリスコ州",
    "バハカリフォルニア州",
    "ユカタン州",
    "ベラクルス州",
    "モンテレイ",
    "グアダラハラ"
  ],
  "韓国": [
    "ソウル",
    "釜山",
    "仁川",
    "大邱",
    "大田",
    "光州",
    "京畿道",
    "慶尚南道",
    "全羅北道",
    "済州"
  ],
  "台湾": [
    "台北",
    "新北",
    "桃園",
    "台中",
    "台南",
    "高雄",
    "新竹",
    "嘉義",
    "彰化",
    "台東",
    "花蓮"
  ]
}
